setup.py
bigos/__init__.py
bigos/__main__.py
bigos.egg-info/PKG-INFO
bigos.egg-info/SOURCES.txt
bigos.egg-info/dependency_links.txt
bigos.egg-info/top_level.txt
bigos/backend/__init__.py
bigos/backend/inotify.py
bigos/backend/polling.py