Metadata-Version: 1.1
Name: bigos
Version: 0.0.2
Summary: Do stuff on file change
Home-page: http://github.com/pstiasny/bigos
Author: Paweł Stiasny
Author-email: pawelstiasny@gmail.com
License: GPL
Keywords: filesystem,event,task
Platform: UNKNOWN
Classifier: Development Status :: 3 - Alpha
Classifier: Environment :: Console
Classifier: Intended Audience :: Developers
Classifier: Intended Audience :: System Administrators
Classifier: License :: OSI Approved :: GNU General Public License v3 or later (GPLv3+)
Classifier: Operating System :: OS Independent
Classifier: Operating System :: POSIX :: Linux
Classifier: Topic :: System :: Filesystems
Classifier: Topic :: Utilities
Classifier: Programming Language :: Python :: 2
Classifier: Programming Language :: Python :: 2.7
